README.md
VERSION
setup.py
oxomo.egg-info/PKG-INFO
oxomo.egg-info/SOURCES.txt
oxomo.egg-info/dependency_links.txt
oxomo.egg-info/requires.txt
oxomo.egg-info/top_level.txt
src/oxomo/__init__.py
src/oxomo/handlers.py