Metadata-Version: 1.1
Name: oxomo
Version: 0.1.2
Summary: 
Home-page: https://gitlab.com/greenhousegroup/ai/libraries/oxomo/
Author: Greenhouse AI team
Author-email: ai@greenhousegroup.com
License: UNKNOWN
Keywords: logging handler https
Platform: UNKNOWN
Classifier: Programming Language :: Python :: 3
Classifier: License :: OSI Approved :: MIT License
Classifier: Operating System :: OS Independent
Classifier: Programming Language :: Python :: 3
